SECFC/__init__.py
SECFC-0.1.1.dist-info/LICENSE
SECFC-0.1.1.dist-info/METADATA
SECFC-0.1.1.dist-info/WHEEL
SECFC-0.1.1.dist-info/top_level.txt
SECFC-0.1.1.dist-info/RECORD
